finance_info/__init__.py
finance_info/__main__.py
finance_info-0.1.0.dist-info/METADATA
finance_info-0.1.0.dist-info/WHEEL
finance_info-0.1.0.dist-info/top_level.txt
finance_info-0.1.0.dist-info/RECORD
